cursive/__init__.py
cursive/certificate_utils.py
cursive/exception.py
cursive/i18n.py
cursive/signature_utils.py
cursive/verifiers.py
cursive/tests/__init__.py
cursive/tests/base.py
cursive/tests/unit/__init__.py
cursive/tests/unit/test_certificate_utils.py
cursive/tests/unit/test_signature_utils.py
cursive/tests/unit/data/child_cert.pem
cursive/tests/unit/data/grandchild_cert.pem
cursive/tests/unit/data/grandparent_cert.pem
cursive/tests/unit/data/not_a_cert.txt
cursive/tests/unit/data/orphaned_cert.pem
cursive/tests/unit/data/parent_cert.pem
cursive/tests/unit/data/self_signed_cert.der
cursive/tests/unit/data/self_signed_cert.pem
cursive/tests/unit/data/self_signed_cert_invalid_ca_constraint.pem
cursive/tests/unit/data/self_signed_cert_invalid_key_usage.pem
cursive/tests/unit/data/self_signed_cert_missing_ca_constraint.pem
cursive/tests/unit/data/self_signed_cert_missing_key_usage.pem
cursive/tests/unit/data/signed_cert.pem
cursive-0.2.3.dist-info/AUTHORS
cursive-0.2.3.dist-info/LICENSE
cursive-0.2.3.dist-info/METADATA
cursive-0.2.3.dist-info/WHEEL
cursive-0.2.3.dist-info/pbr.json
cursive-0.2.3.dist-info/top_level.txt
cursive-0.2.3.dist-info/RECORD
